codemie_test_harness/.env
codemie_test_harness/__init__.py
codemie_test_harness/cli/__init__.py
codemie_test_harness/cli/cli.py
codemie_test_harness/cli/commands/__init__.py
codemie_test_harness/cli/commands/assistant_cmd.py
codemie_test_harness/cli/commands/config_cmd.py
codemie_test_harness/cli/commands/marks_cmd.py
codemie_test_harness/cli/commands/run_cmd.py
codemie_test_harness/cli/commands/workflow_cmd.py
codemie_test_harness/cli/constants.py
codemie_test_harness/cli/marks_utils.py
codemie_test_harness/cli/runner.py
codemie_test_harness/cli/utils.py
codemie_test_harness/pytest.ini
codemie_test_harness/tests/__init__.py
codemie_test_harness/tests/analytics/__init__.py
codemie_test_harness/tests/analytics/test_analytics_endpoints.py
codemie_test_harness/tests/assistant/__init__.py
codemie_test_harness/tests/assistant/datasource/__init__.py
codemie_test_harness/tests/assistant/datasource/provider/__init__.py
codemie_test_harness/tests/assistant/datasource/provider/aice/__init__.py
codemie_test_harness/tests/assistant/datasource/provider/aice/conftest.py
codemie_test_harness/tests/assistant/datasource/provider/aice/test_aice_provider_code_analysis_toolkit.py
codemie_test_harness/tests/assistant/datasource/provider/aice/test_aice_provider_code_exploration_toolkit.py
codemie_test_harness/tests/assistant/datasource/test_azure_devops_wiki_datasource.py
codemie_test_harness/tests/assistant/datasource/test_code_datasource.py
codemie_test_harness/tests/assistant/datasource/test_confluence_datasource.py
codemie_test_harness/tests/assistant/datasource/test_datasource.py
codemie_test_harness/tests/assistant/datasource/test_file_indexing.py
codemie_test_harness/tests/assistant/datasource/test_google_datasource.py
codemie_test_harness/tests/assistant/datasource/test_jira_datasource.py
codemie_test_harness/tests/assistant/default_integrations/__init__.py
codemie_test_harness/tests/assistant/default_integrations/test_default_integrations_for_tool.py
codemie_test_harness-0.1.322.dist-info/METADATA
codemie_test_harness-0.1.322.dist-info/WHEEL
codemie_test_harness-0.1.322.dist-info/entry_points.txt
codemie_test_harness-0.1.322.dist-info/RECORD
